erp/__init__.py
erp/client.py
erp/util/__init__.py
erp/util/config.py
erp/util/headers.py
Gehu_erp-0.4.dist-info/METADATA
Gehu_erp-0.4.dist-info/WHEEL
Gehu_erp-0.4.dist-info/top_level.txt
Gehu_erp-0.4.dist-info/RECORD
