Metadata-Version: 2.1
Name: Gehu-erp
Version: 0.4
Summary: A Python library for interacting with GEHU Student API
Home-page: https://github.com/aminobot22/gehu_erp
Author: yato
Classifier: Programming Language :: Python :: 3
Classifier: License :: OSI Approved :: MIT License
Classifier: Operating System :: OS Independent
Requires-Dist: requests
Requires-Dist: Pillow
Requires-Dist: beautifulsoup4
